WhisperConformer/__init__.py
WhisperConformer/main.py
WhisperConformer-0.0.1.dist-info/METADATA
WhisperConformer-0.0.1.dist-info/WHEEL
WhisperConformer-0.0.1.dist-info/top_level.txt
WhisperConformer-0.0.1.dist-info/RECORD
