Metadata-Version: 2.1
Name: WhisperConformer
Version: 0.0.1
Summary: A library for Whisper Conformer model
Author: thanakronN
Author-email: thanakron.nop@gmail.com
Classifier: Programming Language :: Python :: 3
Classifier: License :: OSI Approved :: MIT License
Classifier: Operating System :: OS Independent
Requires-Python: >=3.10
Requires-Dist: torch >=2.4.0
Requires-Dist: typing-extensions >=4.12.2
Requires-Dist: transformers >=4.42.4
